dopt/__init__.py
dopt/client.py
dopt/core/__init__.py
dopt/core/api_error.py
dopt/core/datetime_utils.py
dopt/core/jsonable_encoder.py
dopt/core/remove_none_from_headers.py
dopt/environment.py
dopt/errors/__init__.py
dopt/errors/bad_request_error.py
dopt/errors/internal_server_error.py
dopt/errors/not_found_error.py
dopt/errors/unauthorized_error.py
dopt/py.typed
dopt/types/__init__.py
dopt/types/bad_request_error_response_body.py
dopt/types/bad_request_error_response_body_code.py
dopt/types/block_transition_query_string.py
dopt/types/block_transition_request_params.py
dopt/types/find_blocks_response.py
dopt/types/find_blocks_response_fields_item.py
dopt/types/find_blocks_response_fields_item_find_blocks_response_fields_item.py
dopt/types/find_blocks_response_state.py
dopt/types/find_blocks_response_type.py
dopt/types/flow_intent_query_string.py
dopt/types/flow_intent_request_intent.py
dopt/types/flow_intent_request_params.py
dopt/types/flow_intent_request_params_intent.py
dopt/types/get_block_query_string.py
dopt/types/get_block_request_params.py
dopt/types/get_flow_query_string.py
dopt/types/get_flow_request_params.py
dopt/types/get_flow_response.py
dopt/types/get_flow_response_blocks_item.py
dopt/types/get_flow_response_blocks_item_fields_item.py
dopt/types/get_flow_response_blocks_item_fields_item_get_flow_response_blocks_item_fields_item.py
dopt/types/get_flow_response_blocks_item_state.py
dopt/types/get_flow_response_blocks_item_type.py
dopt/types/get_flow_response_state.py
dopt/types/health_check_response_body.py
dopt/types/internal_server_error_response_body.py
dopt/types/internal_server_error_response_body_code.py
dopt/types/not_found_error_response_body.py
dopt/types/not_found_error_response_body_code.py
dopt/types/timeout_error_response_body.py
dopt/types/timeout_error_response_body_code.py
dopt/types/unauthorized_error_response_body.py
dopt/types/unauthorized_error_response_body_code.py
fern_dopt-0.0.3.dist-info/METADATA
fern_dopt-0.0.3.dist-info/WHEEL
fern_dopt-0.0.3.dist-info/RECORD
